[{"name":"fasef","address":"efeaf","cuisine":"efefe","website":"https://www.fuckoff.com","description":"efggvsg"},{"name":"fasef","address":"efeaf","cuisine":"efefe","website":"https://www.fuckoff.com","description":"efggvsg"},{"name":"fasef","address":"efeaf","cuisine":"efefe","website":"https://www.fuckoff.com","description":"efggvsg"},{"name":"dfse","address":"fgesg","cuisine":"hhtht","website":"https://www.academshit.com","description":"fpjisroig"},{"name":"grdge","address":"erhgeh","cuisine":"herthert","website":"https://www.fuckoff.com","description":"hrthjrjyrt"}]